clsa_axioma/__init__.py
clsa_axioma-0.1.0.dist-info/WHEEL
clsa_axioma-0.1.0.dist-info/METADATA
clsa_axioma-0.1.0.dist-info/RECORD
