Metadata-Version: 2.1
Name: clsa_axioma
Version: 0.1.0
Summary: Dummy package
Author-email: CLSA <no-reply@clsa.com>
Requires-Dist: flit ; extra == "dev"
Requires-Dist: pre-commit ; extra == "dev"
Provides-Extra: dev
